profasta/__init__.py
profasta/db.py
profasta/decoy.py
profasta/io.py
profasta/parser.py
profasta-0.0.5.dist-info/LICENSE.md
profasta-0.0.5.dist-info/METADATA
profasta-0.0.5.dist-info/WHEEL
profasta-0.0.5.dist-info/top_level.txt
profasta-0.0.5.dist-info/RECORD
