Metadata-Version: 2.1
Name: profasta
Version: 0.0.5
Summary: A Python library for working with protein containing FASTA files.
Author-email: "David M. Hollenstein" <hollenstein.david@gmail.com>
License: MIT License
Project-URL: repository, https://github.com/hollenstein/profasta
Keywords: fasta,bioinformatics,mass spectrometry,proteomics
Classifier: Development Status :: 3 - Alpha
Classifier: License :: OSI Approved :: MIT License
Classifier: Programming Language :: Python :: 3
Classifier: Topic :: Scientific/Engineering :: Bio-Informatics
Requires-Python: >=3.9
License-File: LICENSE.md
Provides-Extra: dev
Requires-Dist: nox ; extra == 'dev'
Requires-Dist: pytest ; extra == 'dev'
Provides-Extra: tests
Requires-Dist: pytest ; extra == 'tests'
